setup.py
golgi/__init__.py
golgi/errors.py
golgi/logging.py
golgi/run.py
golgi.egg-info/PKG-INFO
golgi.egg-info/SOURCES.txt
golgi.egg-info/dependency_links.txt
golgi.egg-info/requires.txt
golgi.egg-info/top_level.txt
golgi/config/__init__.py
golgi/config/errors.py
golgi/config/options.py
golgi/config/write.py
golgi/io/__init__.py
golgi/io/terminal.py