Metadata-Version: 1.0
Name: golgi
Version: 1.8.0
Summary: app config and execution tools
Home-page: UNKNOWN
Author: Torsten Schmits
Author-email: torstenschmits@gmail.com
License: MIT
Platform: UNKNOWN
